__init__.py
napari_threedee/__init__.py
napari_threedee/_sample_data.py
napari_threedee/_version.py
napari_threedee/conftest.py
napari_threedee/dock_widgets.py
napari_threedee/napari.yaml
napari_threedee/vispy.py
napari_threedee/_backend/__init__.py
napari_threedee/_backend/threedee_model.py
napari_threedee/_backend/threedee_widget_base.py
napari_threedee/_backend/manipulator/__init__.py
napari_threedee/_backend/manipulator/_interface.py
napari_threedee/_backend/manipulator/axis_model.py
napari_threedee/_backend/manipulator/central_axis.py
napari_threedee/_backend/manipulator/drag_managers.py
napari_threedee/_backend/manipulator/manipulator_model.py
napari_threedee/_backend/manipulator/napari_manipulator_backend.py
napari_threedee/_backend/manipulator/rotator.py
napari_threedee/_backend/manipulator/translator.py
napari_threedee/_backend/manipulator/utils.py
napari_threedee/_backend/manipulator/vispy_manipulator_visual.py
napari_threedee/_backend/manipulator/vispy_visual_data.py
napari_threedee/_backend/manipulator/_tests/__init__.py
napari_threedee/_backend/manipulator/_tests/test_axis_model.py
napari_threedee/_backend/manipulator/_tests/test_central_axis.py
napari_threedee/_backend/manipulator/_tests/test_drag_manager.py
napari_threedee/_backend/manipulator/_tests/test_manipulator.py
napari_threedee/_backend/manipulator/_tests/test_manipulator_visual_data.py
napari_threedee/_backend/manipulator/_tests/test_rotator.py
napari_threedee/_backend/manipulator/_tests/test_translator.py
napari_threedee/_tests/__init__.py
napari_threedee/_tests/test_dock_widget.py
napari_threedee/annotators/__init__.py
napari_threedee/annotators/base.py
napari_threedee/annotators/constants.py
napari_threedee/annotators/_qt/__init__.py
napari_threedee/annotators/_qt/qt_label_annotator.py
napari_threedee/annotators/_qt/qt_path_annotator.py
napari_threedee/annotators/_qt/qt_plane_point_annotator.py
napari_threedee/annotators/_qt/qt_point_annotator.py
napari_threedee-0.0.29.dist-info/METADATA
napari_threedee-0.0.29.dist-info/WHEEL
napari_threedee-0.0.29.dist-info/entry_points.txt
napari_threedee-0.0.29.dist-info/licenses/LICENSE
napari_threedee-0.0.29.dist-info/RECORD
