Metadata-Version: 2.4
Name: napari-threedee
Version: 0.0.29
Summary: A suite of useful tools based on 3D interactivity in napari
Project-URL: homepage, https://github.com/alisterburt/napari-threedee
Project-URL: repository, https://github.com/napari-threedee/napari-threedee
Project-URL: Bug Tracker, https://github.com/napari-threedee/napari-threedee/issues
Project-URL: Documentation, https://github.com/napari-threedee/napari-threedee#README.md
Project-URL: Source Code, https://github.com/napari-threedee/napari-threedee
Project-URL: User Support, https://github.com/napari-threedee/napari-threedee/issues
Author-email: napari team <napari-steering-council@googlegroups.com>
License: BSD-3-Clause
License-File: LICENSE
Classifier: Development Status :: 2 - Pre-Alpha
Classifier: Framework :: napari
Classifier: Intended Audience :: Developers
Classifier: License :: OSI Approved :: BSD License
Classifier: Operating System :: OS Independent
Classifier: Programming Language :: Python
Classifier: Programming Language :: Python :: 3
Classifier: Programming Language :: Python :: 3.10
Classifier: Programming Language :: Python :: 3.11
Classifier: Programming Language :: Python :: 3.12
Classifier: Programming Language :: Python :: 3.13
Classifier: Topic :: Software Development :: Testing
Requires-Python: >=3.10
Requires-Dist: einops
Requires-Dist: imageio!=2.11.0,!=2.22.1,>=2.5.0
Requires-Dist: libigl
Requires-Dist: magicgui
Requires-Dist: morphosamplers
Requires-Dist: mrcfile
Requires-Dist: napari>=0.5.0
Requires-Dist: numpy
Requires-Dist: pandas
Requires-Dist: pooch
Requires-Dist: psygnal
Requires-Dist: pydantic
Requires-Dist: qtpy
Requires-Dist: scipy
Requires-Dist: superqt
Requires-Dist: vispy
Requires-Dist: zarr<3
Provides-Extra: dev
Requires-Dist: lxml[html-clean]>5; extra == 'dev'
Requires-Dist: mkdocs; extra == 'dev'
Requires-Dist: mkdocs-gallery>0.7.6; extra == 'dev'
Requires-Dist: mkdocs-material; extra == 'dev'
Requires-Dist: mkdocs-video; extra == 'dev'
Requires-Dist: mkdocstrings[python]; extra == 'dev'
Requires-Dist: pytest; extra == 'dev'
Requires-Dist: pytest-qt; extra == 'dev'
Requires-Dist: qtgallery; extra == 'dev'
Requires-Dist: scikit-image[data]; extra == 'dev'
